Topsis_Shaurya_102317151/__init__.py
Topsis_Shaurya_102317151/topsis.py
topsis_shaurya_102317151-1.0.1.dist-info/METADATA
topsis_shaurya_102317151-1.0.1.dist-info/WHEEL
topsis_shaurya_102317151-1.0.1.dist-info/entry_points.txt
topsis_shaurya_102317151-1.0.1.dist-info/top_level.txt
topsis_shaurya_102317151-1.0.1.dist-info/RECORD
