Metadata-Version: 2.4
Name: Topsis-Shaurya-102317151
Version: 1.0.1
Summary: A package for Topsis
Author: Shaurya Verma
Author-email: sverma1_be23@thapar.edu
Requires-Dist: pandas
Requires-Dist: numpy
Dynamic: author
Dynamic: author-email
Dynamic: description
Dynamic: description-content-type
Dynamic: requires-dist
Dynamic: summary
